pack_jb_stats/__init__.py
pack_jb_stats/power_stat.py
pack_jb_stats-0.1.3.dist-info/METADATA
pack_jb_stats-0.1.3.dist-info/WHEEL
pack_jb_stats-0.1.3.dist-info/top_level.txt
pack_jb_stats-0.1.3.dist-info/RECORD
