Metadata-Version: 2.2
Name: pack_jb_stats
Version: 0.1.3
Requires-Dist: scipy
Requires-Dist: numpy
Dynamic: description
Dynamic: description-content-type
Dynamic: requires-dist
